spielmacher/__init__.py
spielmacher/game.py
spielmacher/player.py
spielmacher/tournament.py
spielmacher-0.0.3.dist-info/METADATA
spielmacher-0.0.3.dist-info/WHEEL
spielmacher-0.0.3.dist-info/licenses/LICENSE
spielmacher-0.0.3.dist-info/RECORD
